painlesspy/__init__.py
painlesspy/index.py
painlesspy/main.py
painlesspy-0.0.2.dist-info/METADATA
painlesspy-0.0.2.dist-info/WHEEL
painlesspy-0.0.2.dist-info/top_level.txt
painlesspy-0.0.2.dist-info/RECORD
